{
  "Basicmon0": {
    "name": "Basicmon",
    "max_health": "50",
    "health": 50,
    "damage": 15,
    "statusEffects": "",
    "experience": 50
  },
  "Basicmon1": {
    "name": "Basicmon",
    "max_health": "50",
    "health": 50,
    "damage": 15,
    "statusEffects": "",
    "experience": 50
  },
  "Basicmon2": {
    "name": "Basicmon",
    "max_health": "50",
    "health": 50,
    "damage": 15,
    "statusEffects": "",
    "experience": 50
  },
  "Basicmon3": {
    "name": "Basicmon",
    "max_health": "50",
    "health": 50,
    "damage": 15,
    "statusEffects": "",
    "experience": 50
  },
  "Basicmon4": {
    "name": "Basicmon",
    "max_health": "50",
    "health": 50,
    "damage": 15,
    "statusEffects": "",
    "experience": 50
  },
  "Pumpkino": {
    "name": "Pumpkino",
    "max_health": 20,
    "health": 20,
    "damage": 50,
    "statusEffects": "",
    "experience": 100
  },
  "Reaper": {
    "name": "Reaper",
    "max_health": 100,
    "health": 100,
    "damage": 100,
    "statusEffects": "",
    "experience": 200
  }
}
